blackmirror.py
blackmirror-1.0.0.dist-info/LICENSE
blackmirror-1.0.0.dist-info/METADATA
blackmirror-1.0.0.dist-info/WHEEL
blackmirror-1.0.0.dist-info/entry_points.txt
blackmirror-1.0.0.dist-info/top_level.txt
blackmirror-1.0.0.dist-info/RECORD
